{"files": [{"name": "最小高度树.md", "relapath": "./blogs/leetcode/最小高度树.md", "updatetime": {"year": 2022, "mon": 8, "day": 13, "hour": 13, "min": 16, "sec": 18}}, {"name": "动态规划：最佳买卖股票时机.md", "relapath": "./blogs/leetcode/动态规划：最佳买卖股票时机.md", "updatetime": {"year": 2022, "mon": 8, "day": 13, "hour": 9, "min": 34, "sec": 22}}, {"name": "README.md", "relapath": "./blogs/leetcode/README.md", "updatetime": {"year": 2022, "mon": 8, "day": 10, "hour": 22, "min": 27, "sec": 35}}, {"name": "动态规划最大正方形.md", "relapath": "./blogs/leetcode/动态规划最大正方形.md", "updatetime": {"year": 2022, "mon": 7, "day": 24, "hour": 9, "min": 10, "sec": 36}}, {"name": "两数求和.md", "relapath": "./blogs/leetcode/两数求和.md", "updatetime": {"year": 2022, "mon": 6, "day": 18, "hour": 10, "min": 8, "sec": 53}}, {"name": "c++中的map和unordered_map.md", "relapath": "./blogs/leetcode/c++中的map和unordered_map.md", "updatetime": {"year": 2022, "mon": 6, "day": 17, "hour": 13, "min": 32, "sec": 45}}, {"name": "清单.md", "relapath": "./blogs/leetcode/清单.md", "updatetime": {"year": 2022, "mon": 6, "day": 17, "hour": 9, "min": 40, "sec": 26}}], "pages": [{"page": 1, "files": [{"name": "最小高度树.md", "relapath": "./blogs/leetcode/最小高度树.md", "updatetime": {"year": 2022, "mon": 8, "day": 13, "hour": 13, "min": 16, "sec": 18}}, {"name": "动态规划：最佳买卖股票时机.md", "relapath": "./blogs/leetcode/动态规划：最佳买卖股票时机.md", "updatetime": {"year": 2022, "mon": 8, "day": 13, "hour": 9, "min": 34, "sec": 22}}, {"name": "README.md", "relapath": "./blogs/leetcode/README.md", "updatetime": {"year": 2022, "mon": 8, "day": 10, "hour": 22, "min": 27, "sec": 35}}, {"name": "动态规划最大正方形.md", "relapath": "./blogs/leetcode/动态规划最大正方形.md", "updatetime": {"year": 2022, "mon": 7, "day": 24, "hour": 9, "min": 10, "sec": 36}}, {"name": "两数求和.md", "relapath": "./blogs/leetcode/两数求和.md", "updatetime": {"year": 2022, "mon": 6, "day": 18, "hour": 10, "min": 8, "sec": 53}}]}, {"page": 2, "files": [{"name": "c++中的map和unordered_map.md", "relapath": "./blogs/leetcode/c++中的map和unordered_map.md", "updatetime": {"year": 2022, "mon": 6, "day": 17, "hour": 13, "min": 32, "sec": 45}}, {"name": "清单.md", "relapath": "./blogs/leetcode/清单.md", "updatetime": {"year": 2022, "mon": 6, "day": 17, "hour": 9, "min": 40, "sec": 26}}]}], "totalPage": 2}